pyrlprob/__init__.py
pyrlprob/__main__.py
pyrlprob/base_funs.py
pyrlprob/commands.py
pyrlprob/mdp.py
pyrlprob/problem.py
pyrlprob/include/pyrlprob/binding.cpp
pyrlprob/include/pyrlprob/mdp.h
pyrlprob/include/pyrlprob/mdp_vec.h
pyrlprob/include/pyrlprob/py_mdp.h
pyrlprob/tests/__init__.py
pyrlprob/tests/landing1d_cpp.yaml
pyrlprob/tests/landing1d_load.yaml
pyrlprob/tests/landing1d_py.yaml
pyrlprob/tests/test_landing1d.py
pyrlprob/tests/test_multiple_gym.py
pyrlprob/tests/cpp_tests/__init__.py
pyrlprob/tests/cpp_tests/binding.cpp
pyrlprob/tests/cpp_tests/landing1d.cpp
pyrlprob/tests/cpp_tests/landing1d.h
pyrlprob/tests/cpp_tests/landing1d.py
pyrlprob/tests/cpp_tests/landing1d_cpp.cpython-38-x86_64-linux-gnu.so
pyrlprob/tests/cpp_tests/landing1d_dyn.h
pyrlprob/tests/cpp_tests/rk4.h
pyrlprob/tests/py_tests/__init__.py
pyrlprob/tests/py_tests/landing1d.py
pyrlprob/tests/py_tests/landing1d_dyn.py
pyrlprob/tests/py_tests/landing1d_gym.py
pyrlprob/tests/py_tests/tuned_examples/Breakout-v0_A2C.yaml
pyrlprob/tests/py_tests/tuned_examples/Breakout-v0_DQN.yaml
pyrlprob/tests/py_tests/tuned_examples/Breakout-v0_PG.yaml
pyrlprob/tests/py_tests/tuned_examples/Breakout-v0_PPO.yaml
pyrlprob/tests/py_tests/tuned_examples/Breakout-v0_SAC.yaml
pyrlprob/tests/py_tests/tuned_examples/CartPole-v1_A2C.yaml
pyrlprob/tests/py_tests/tuned_examples/CartPole-v1_DQN.yaml
pyrlprob/tests/py_tests/tuned_examples/CartPole-v1_PG.yaml
pyrlprob/tests/py_tests/tuned_examples/CartPole-v1_PPO.yaml
pyrlprob/tests/py_tests/tuned_examples/CartPole-v1_SAC.yaml
pyrlprob/tests/py_tests/tuned_examples/Landing1D_A2C.yaml
pyrlprob/tests/py_tests/tuned_examples/Landing1D_PG.yaml
pyrlprob/tests/py_tests/tuned_examples/Landing1D_PPO.yaml
pyrlprob/tests/py_tests/tuned_examples/Landing1D_SAC.yaml
pyrlprob/tests/py_tests/tuned_examples/Landing1D_TD3.yaml
pyrlprob/tests/py_tests/tuned_examples/Pendulum-v1_A2C.yaml
pyrlprob/tests/py_tests/tuned_examples/Pendulum-v1_PG.yaml
pyrlprob-1.7.4.dist-info/LICENSE.txt
pyrlprob-1.7.4.dist-info/METADATA
pyrlprob-1.7.4.dist-info/WHEEL
pyrlprob-1.7.4.dist-info/top_level.txt
pyrlprob-1.7.4.dist-info/RECORD
