Metadata-Version: 2.1
Name: pyrlprob
Version: 1.7.4
Summary: Train easily Gym-derived environments in python/C++ through Ray RLlib
Home-page: https://github.com/LorenzoFederici/pyrlprob
Author: Lorenzo Federici
Author-email: federicilorenzo94@gmail.com
Classifier: Programming Language :: Python :: 3
Classifier: License :: OSI Approved :: MIT License
Classifier: Operating System :: OS Independent
Requires-Python: >=3.8
License-File: LICENSE.txt
Requires-Dist: dm-tree
Requires-Dist: gym
Requires-Dist: lz4
Requires-Dist: matplotlib
Requires-Dist: numpy
Requires-Dist: pandas
Requires-Dist: pybind11
Requires-Dist: pytest
Requires-Dist: ray (==1.6.0)
Requires-Dist: scipy
Requires-Dist: scikit-image
Requires-Dist: tabulate
Requires-Dist: tensorflow
Requires-Dist: torch
Requires-Dist: typing
Requires-Dist: PyYAML
Requires-Dist: opencv-python ; platform_machine == "x86_64"
Requires-Dist: tensorboardx ; platform_machine == "x86_64"
